notecron/__init__.py
notecron/center/__init__.py
notecron/center/app.py
notecron/center/models.py
notecron/center/common/__init__.py
notecron/center/common/database.py
notecron/center/common/functions.py
notecron/center/common/config/__init__.py
notecron/center/common/config/config.py
notecron/center/common/scheduler/CuBackgroundScheduler.py
notecron/center/common/scheduler/CuGeventScheduler.py
notecron/center/common/scheduler/__init__.py
notecron/center/pages/__init__.py
notecron/center/pages/decorated.py
notecron/center/pages/api/__init__.py
notecron/center/pages/api/core.py
notecron/center/pages/api/views.py
notecron/center/pages/crons/__init__.py
notecron/center/pages/crons/core.py
notecron/center/pages/main/__init__.py
notecron/center/pages/main/core.py
notecron/center/pages/main/errors.py
notecron/center/pages/main/views.py
notecron/center/static/__init__.py
notecron/center/static/jquery.js
notecron/center/static/vue.js
notecron/center/static/images/__init__.py
notecron/center/static/images/mini_code.png
notecron/center/static/js/__init__.py
notecron/center/static/js/ajaxForm.js
notecron/center/static/js/common.js
notecron/center/static/js/jquery.js
notecron/center/static/js/md5.js
notecron/center/static/js/qrcode.min.js
notecron/center/static/js/requests.js
notecron/center/static/js/signs.js
notecron/center/static/js/wind.js
notecron/center/static/js/artDialog/__init__.py
notecron/center/static/js/artDialog/artDialog.extend.js
notecron/center/static/js/artDialog/artDialog.js
notecron/center/static/js/artDialog/iframeTools.js
notecron/center/static/js/artDialog/skins/__init__.py
notecron/center/static/js/artDialog/skins/blue.css
notecron/center/static/js/artDialog/skins/default.css
notecron/center/static/js/artDialog/skins/blue/__init__.py
notecron/center/static/js/artDialog/skins/blue/bg.png
notecron/center/static/js/artDialog/skins/blue/bg2.png
notecron/center/static/js/artDialog/skins/blue/bg_css3.png
notecron-0.5.5.dist-info/LICENSE
notecron-0.5.5.dist-info/METADATA
notecron-0.5.5.dist-info/WHEEL
notecron-0.5.5.dist-info/entry_points.txt
notecron-0.5.5.dist-info/top_level.txt
notecron-0.5.5.dist-info/RECORD
