Metadata-Version: 2.1
Name: notecron
Version: 0.5.5
Summary: notecron
Home-page: https://github.com/1007530194
Author: niuliangtao
Author-email: 1007530194@qq.com
License-File: LICENSE
Requires-Dist: apscheduler
Requires-Dist: gunicorn
Requires-Dist: records
Requires-Dist: notedata
Requires-Dist: gevent
